[
    {
      "ASSEMBLY SEAT NO": "1",
      "ASSEMBLY NAME": "Abdasa",
      "CANDIDATE NAME": "Vasant Valjibhai Khetani",
      "Facebook Profile Link": "Not Available",
      "Twitter link": "Not Available",
      "Place": "Not Available",
      "Designation": "Not Available",
      "Mobile No.": "Not Available"
    },
    {
      "ASSEMBLY SEAT NO": "2",
      "ASSEMBLY NAME": "Mandvi (Kachchh)",
      "CANDIDATE NAME": "KAILASH GADHVI",
      "Facebook Profile Link": "https://www.facebook.com/kailashkumarkgadhvi ",
      "Twitter link": "https://twitter.com/kailashkgadhvi ",
      "Place": "Ahmedabad ",
      "Designation": "State Treasurer (ખજાનચી), આમ આદમી પાર્ટી ગુજરાત",
      "Mobile No.": "9825325145"
    },
    {
      "ASSEMBLY SEAT NO": "3",
      "ASSEMBLY NAME": "Bhuj",
      "CANDIDATE NAME": "RAJESH PANDORIYA",
      "Facebook Profile Link": "https://www.facebook.com/rajesh.pindoriya.549",
      "Twitter link": "Not Available",
      "Place": "Bhuj",
      "Designation": "Not Available",
      "Mobile No.": "Not Available"
    },
    {
      "ASSEMBLY SEAT NO": "4",
      "ASSEMBLY NAME": "Anjar",
      "CANDIDATE NAME": "Arajan Rabari",
      "Facebook Profile Link": "Not Available",
      "Twitter link": "Not Available",
      "Place": "Not Available",
      "Designation": "Not Available",
      "Mobile No.": "Not Available"
    },
    {
      "ASSEMBLY SEAT NO": "5",
      "ASSEMBLY NAME": "Gandhidham",
      "CANDIDATE NAME": "BT maheshwari",
      "Facebook Profile Link": "Not Available",
      "Twitter link": "Not Available",
      "Place": "Not Available",
      "Designation": "Not Available",
      "Mobile No.": "Not Available"
    },
    {
      "ASSEMBLY SEAT NO": "6",
      "ASSEMBLY NAME": "Rapar",
      "CANDIDATE NAME": "AMBALAL PATEL",
      "Facebook Profile Link": "https://www.facebook.com/profile.php?id=100084852352081 ",
      "Twitter link": "Not Available",
      "Place": "Not Available",
      "Designation": "Not Available",
      "Mobile No.": "9920693306"
    },
    {
      "ASSEMBLY SEAT NO": "7",
      "ASSEMBLY NAME": "Vav",
      "CANDIDATE NAME": "Dr Bhim Patel",
      "Facebook Profile Link": "https://www.facebook.com/bhim.patel",
      "Twitter link": "https://twitter.com/dr_bhimpatel",
      "Place": "Not Available",
      "Designation": "AAP Loksabha Secretary (Banaskantha)",
      "Mobile No.": "Not Available"
    },
    {
      "ASSEMBLY SEAT NO": "8",
      "ASSEMBLY NAME": "Tharad",
      "CANDIDATE NAME": "Virchandbhai Chelabhai Chavda",
      "Facebook Profile Link": "Not Available",
      "Twitter link": "Not Available",
      "Place": "Not Available",
      "Designation": "Not Available",
      "Mobile No.": "Not Available"
    },
    {
      "ASSEMBLY SEAT NO": "9",
      "ASSEMBLY NAME": "Dhanera",
      "CANDIDATE NAME": "Suresh Devda",
      "Facebook Profile Link": "https://www.facebook.com/suraj.devda",
      "Twitter link": "Not Available",
      "Place": "Deesa",
      "Designation": "Not Available",
      "Mobile No.": "9574070600"
    },
    {
      "ASSEMBLY SEAT NO": "10",
      "ASSEMBLY NAME": "Danta (ST)",
      "CANDIDATE NAME": "MK Bombadiya",
      "Facebook Profile Link": "Not Available",
      "Twitter link": "Not Available",
      "Place": "Not Available",
      "Designation": "Not Available",
      "Mobile No.": "Not Available"
    },
    {
      "ASSEMBLY SEAT NO": "11",
      "ASSEMBLY NAME": "Vadgam (SC)",
      "CANDIDATE NAME": "DALPAT BHATIYA",
      "Facebook Profile Link": "https://www.facebook.com/profile.php?id=100086163789857 ",
      "Twitter link": "Not Available",
      "Place": "Vadgam",
      "Designation": "Not Available",
      "Mobile No.": "Not Available"
    },
    {
      "ASSEMBLY SEAT NO": "12",
      "ASSEMBLY NAME": "Palanpur",
      "CANDIDATE NAME": "Ramesh Nabhani",
      "Facebook Profile Link": "Not Available",
      "Twitter link": "Not Available",
      "Place": "Not Available",
      "Designation": "Not Available",
      "Mobile No.": "Not Available"
    },
    {
      "ASSEMBLY SEAT NO": "13",
      "ASSEMBLY NAME": "Deesa",
      "CANDIDATE NAME": "DR RAMESH PATEL",
      "Facebook Profile Link": "https://www.facebook.com/Dr.ramesh.I.patel ",
      "Twitter link": "https://twitter.com/AAMADAMIPARTY3 ",
      "Place": "Not Available",
      "Designation": "Not Available",
      "Mobile No.": "63573 24004"
    },
    {
      "ASSEMBLY SEAT NO": "14",
      "ASSEMBLY NAME": "Deodar",
      "CANDIDATE NAME": "BHEMABHAI CHAUDHARY",
      "Facebook Profile Link": "https://www.facebook.com/aapkaBRchaudhary ",
      "Twitter link": "https://twitter.com/BHEMABHAI",
      "Place": "Not Available",
      "Designation": " પ્રદેશ ઉપાધ્યક્ષ,આમ આદમી પાર્ટી ગુજરાત",
      "Mobile No.": "9724717450"
    },
    {
      "ASSEMBLY SEAT NO": "15",
      "ASSEMBLY NAME": "Kankrej",
      "CANDIDATE NAME": "Mukesh Thakkar",
      "Facebook Profile Link": "Not Available",
      "Twitter link": "Not Available",
      "Place": "Not Available",
      "Designation": "Not Available",
      "Mobile No.": "Not Available"
    },
    {
      "ASSEMBLY SEAT NO": "16",
      "ASSEMBLY NAME": "Radhanpur",
      "CANDIDATE NAME": "Lalaji Thakor Radhanpur",
      "Facebook Profile Link": "https://www.facebook.com/lalaji.thakor.927",
      "Twitter link": "https://twitter.com/Iamlalajithakor?fbclid=IwAR0obYDvqfyjlXRt9qg3P5_UnT3lNwPaYR7h3aax7crtsKV4iKSCa1iSOro",
      "Place": "Radhanpur",
      "Designation": "Not Available",
      "Mobile No.": "6351150894"
    },
    {
      "ASSEMBLY SEAT NO": "17",
      "ASSEMBLY NAME": "Chanasma",
      "CANDIDATE NAME": "Vishnu Patel",
      "Facebook Profile Link": "Not Available",
      "Twitter link": "Not Available",
      "Place": "Not Available",
      "Designation": "Not Available",
      "Mobile No.": "Not Available"
    },
    {
      "ASSEMBLY SEAT NO": "18",
      "ASSEMBLY NAME": "Patan",
      "CANDIDATE NAME": "LALESH THAKKAR",
      "Facebook Profile Link": "https://www.facebook.com/laleshkumar.thakkar ",
      "Twitter link": "https://twitter.com/thakkar_lalesh ",
      "Place": "Patan",
      "Designation": "Not Available",
      "Mobile No.": "9909314442"
    },
    {
      "ASSEMBLY SEAT NO": "19",
      "ASSEMBLY NAME": "Sidhpur",
      "CANDIDATE NAME": "Mahendra Rajput",
      "Facebook Profile Link": "Not Available",
      "Twitter link": "Not Available",
      "Place": "Not Available",
      "Designation": "Not Available",
      "Mobile No.": "Not Available"
    },
    {
      "ASSEMBLY SEAT NO": "20",
      "ASSEMBLY NAME": "Kheralu",
      "CANDIDATE NAME": "Dinesh Thakor",
      "Facebook Profile Link": "Not Available",
      "Twitter link": "Not Available",
      "Place": "Not Available",
      "Designation": "Not Available",
      "Mobile No.": "Not Available"
    },
    {
      "ASSEMBLY SEAT NO": "21",
      "ASSEMBLY NAME": "Unjha",
      "CANDIDATE NAME": "Urvish Patel",
      "Facebook Profile Link": "https://www.facebook.com/profile.php?id=100087779075163",
      "Twitter link": "Not Available",
      "Place": "Not Available",
      "Designation": "Not Available",
      "Mobile No.": "9054515384"
    },
    {
      "ASSEMBLY SEAT NO": "22",
      "ASSEMBLY NAME": "Visnagar",
      "CANDIDATE NAME": "Jayantilal M Patel",
      "Facebook Profile Link": "Not Available",
      "Twitter link": "Not Available",
      "Place": "Not Available",
      "Designation": "Not Available",
      "Mobile No.": "Not Available"
    },
    {
      "ASSEMBLY SEAT NO": "23",
      "ASSEMBLY NAME": "Bechraji",
      "CANDIDATE NAME": "SAGAR RABARI",
      "Facebook Profile Link": "https://www.facebook.com/Saggar.Rabari",
      "Twitter link": "Not Available",
      "Place": "becharaji",
      "Designation": "ઉપપરમુખ, આમ આદમી પાર્ટી ગુજરાત",
      "Mobile No.": "Not Available"
    },
    {
      "ASSEMBLY SEAT NO": "24",
      "ASSEMBLY NAME": "Kadi (SC)",
      "CANDIDATE NAME": "H K DABHI",
      "Facebook Profile Link": "Not Available",
      "Twitter link": "Not Available",
      "Place": "Not Available",
      "Designation": "Not Available",
      "Mobile No.": "Not Available"
    },
    {
      "ASSEMBLY SEAT NO": "25",
      "ASSEMBLY NAME": "Mehsana",
      "CANDIDATE NAME": "DISHANT PATEL(BHAGAT )",
      "Facebook Profile Link": "https://www.facebook.com/bhagatpatelmehsana",
      "Twitter link": "Not Available",
      "Place": "Not Available",
      "Designation": "Not Available",
      "Mobile No.": "Not Available"
    },
    {
      "ASSEMBLY SEAT NO": "26",
      "ASSEMBLY NAME": "Vijapur",
      "CANDIDATE NAME": "CHIRAG PATEL",
      "Facebook Profile Link": "https://www.facebook.com/profile.php?id=100015311070106",
      "Twitter link": "Not Available",
      "Place": "Not Available",
      "Designation": "Not Available",
      "Mobile No.": "Not Available"
    },
    {
      "ASSEMBLY SEAT NO": "27",
      "ASSEMBLY NAME": "Himatnagar",
      "CANDIDATE NAME": "NIRMALSINH PARMAR",
      "Facebook Profile Link": "https://www.facebook.com/nirmalsinh.parmar.5245 ",
      "Twitter link": "Not Available",
      "Place": "Not Available",
      "Designation": "Not Available",
      "Mobile No.": "Not Available"
    },
    {
      "ASSEMBLY SEAT NO": "28",
      "ASSEMBLY NAME": "Idar (SC)",
      "CANDIDATE NAME": "JAYANTIBHAI PARNAMI",
      "Facebook Profile Link": "https://www.facebook.com/pranami.jayntibahi ",
      "Twitter link": "Not Available",
      "Place": "Not Available",
      "Designation": "Not Available",
      "Mobile No.": "Not Available"
    },
    {
      "ASSEMBLY SEAT NO": "29",
      "ASSEMBLY NAME": "Khedbrahma (ST)",
      "CANDIDATE NAME": "BIPIN GAMETI",
      "Facebook Profile Link": "https://www.facebook.com/bipin.gameti.39 ",
      "Twitter link": "Not Available",
      "Place": "Not Available",
      "Designation": "Not Available",
      "Mobile No.": "Not Available"
    },
    {
      "ASSEMBLY SEAT NO": "30",
      "ASSEMBLY NAME": "Bhiloda (ST)",
      "CANDIDATE NAME": "RUPSINH BHAGODA",
      "Facebook Profile Link": "https://www.facebook.com/profile.php?id=100084141741807 ",
      "Twitter link": "Not Available",
      "Place": "Not Available",
      "Designation": "Not Available",
      "Mobile No.": "Not Available"
    },
    {
      "ASSEMBLY SEAT NO": "31",
      "ASSEMBLY NAME": "Modasa",
      "CANDIDATE NAME": "Rajendrasinh Parmar",
      "Facebook Profile Link": "Not Available",
      "Twitter link": "Not Available",
      "Place": "Not Available",
      "Designation": "Not Available",
      "Mobile No.": "Not Available"
    },
    {
      "ASSEMBLY SEAT NO": "32",
      "ASSEMBLY NAME": "Bayad",
      "CANDIDATE NAME": "CHHUNNIBHAI PATEL",
      "Facebook Profile Link": "https://www.facebook.com/aapbayadmalpur",
      "Twitter link": "Not Available",
      "Place": "Not Available",
      "Designation": "Not Available",
      "Mobile No.": "Not Available"
    },
    {
      "ASSEMBLY SEAT NO": "33",
      "ASSEMBLY NAME": "Prantij",
      "CANDIDATE NAME": "ALPESH PATEL",
      "Facebook Profile Link": "https://www.facebook.com/profile.php?id=100071327725366",
      "Twitter link": "Not Available",
      "Place": "Not Available",
      "Designation": "Not Available",
      "Mobile No.": "Not Available"
    },
    {
      "ASSEMBLY SEAT NO": "34",
      "ASSEMBLY NAME": "Dahegam",
      "CANDIDATE NAME": "Suhag Panchal",
      "Facebook Profile Link": "Not Available",
      "Twitter link": "Not Available",
      "Place": "Not Available",
      "Designation": "Not Available",
      "Mobile No.": "Not Available"
    },
    {
      "ASSEMBLY SEAT NO": "35",
      "ASSEMBLY NAME": "Gandhinagar South",
      "CANDIDATE NAME": "DOLAT PATEL",
      "Facebook Profile Link": "https://www.facebook.com/Dolat.devendrapatel/",
      "Twitter link": "https://twitter.com/DolatPatelAAP ",
      "Place": "Ahmedabad",
      "Designation": "State joint Secretary, AAP, Gujarat",
      "Mobile No.": "9898194908"
    },
    {
      "ASSEMBLY SEAT NO": "36",
      "ASSEMBLY NAME": "Gandhinagar North",
      "CANDIDATE NAME": "MUKESH PATEL",
      "Facebook Profile Link": "Not Available",
      "Twitter link": "https://twitter.com/MukeshP61250205 ",
      "Place": "Not Available",
      "Designation": "Not Available",
      "Mobile No.": "9426302684"
    },
    {
      "ASSEMBLY SEAT NO": "37",
      "ASSEMBLY NAME": "Mansa",
      "CANDIDATE NAME": "Bhaskar Patel ",
      "Facebook Profile Link": "Not Available",
      "Twitter link": "Not Available",
      "Place": "Not Available",
      "Designation": "Not Available",
      "Mobile No.": "Not Available"
    },
    {
      "ASSEMBLY SEAT NO": "38",
      "ASSEMBLY NAME": "Kalol",
      "CANDIDATE NAME": "Kantiji Thakor",
      "Facebook Profile Link": "Not Available",
      "Twitter link": "Not Available",
      "Place": "Not Available",
      "Designation": "Not Available",
      "Mobile No.": "Not Available"
    },
    {
      "ASSEMBLY SEAT NO": "39",
      "ASSEMBLY NAME": "Viramgam",
      "CANDIDATE NAME": "Kuvarji Thakor",
      "Facebook Profile Link": "Not Available",
      "Twitter link": "Not Available",
      "Place": "Not Available",
      "Designation": "Not Available",
      "Mobile No.": "Not Available"
    },
    {
      "ASSEMBLY SEAT NO": "40",
      "ASSEMBLY NAME": "Sanand",
      "CANDIDATE NAME": "KULDEEP VAGHELA",
      "Facebook Profile Link": "https://www.facebook.com/profile.php?id=100086577057357 ",
      "Twitter link": "Not Available",
      "Place": "Not Available",
      "Designation": "Not Available",
      "Mobile No.": "Not Available"
    },
    {
      "ASSEMBLY SEAT NO": "41",
      "ASSEMBLY NAME": "Ghatlodia",
      "CANDIDATE NAME": "VIJAYPATEL",
      "Facebook Profile Link": "https://www.facebook.com/VijayPatelGhatlodiya/ ",
      "Twitter link": "https://twitter.com/AAPGhatlodiya ",
      "Place": "Not Available",
      "Designation": "Not Available",
      "Mobile No.": "9574114422"
    },
    {
      "ASSEMBLY SEAT NO": "42",
      "ASSEMBLY NAME": "Vejalpur",
      "CANDIDATE NAME": "KALPESH PATEL",
      "Facebook Profile Link": "https://www.facebook.com/kalpeshpatel.bholabhai ",
      "Twitter link": "https://twitter.com/KalpeshBhola",
      "Place": "Not Available",
      "Designation": "Not Available",
      "Mobile No.": "Not Available"
    },
    {
      "ASSEMBLY SEAT NO": "43",
      "ASSEMBLY NAME": "Vatva",
      "CANDIDATE NAME": "BIPIN PATEL",
      "Facebook Profile Link": "https://www.facebook.com/bipinbhaipatelgujarat",
      "Twitter link": "Not Available",
      "Place": "Not Available",
      "Designation": "Not Available",
      "Mobile No.": "Not Available"
    },
    {
      "ASSEMBLY SEAT NO": "44",
      "ASSEMBLY NAME": "Ellis Bridge",
      "CANDIDATE NAME": "Paras shah ",
      "Facebook Profile Link": "Not Available",
      "Twitter link": "Not Available",
      "Place": "Not Available",
      "Designation": "Not Available",
      "Mobile No.": "Not Available"
    },
    {
      "ASSEMBLY SEAT NO": "45",
      "ASSEMBLY NAME": "Naranpura",
      "CANDIDATE NAME": "Pankaj Patel",
      "Facebook Profile Link": "Not Available",
      "Twitter link": "Not Available",
      "Place": "Not Available",
      "Designation": "Not Available",
      "Mobile No.": "Not Available"
    },
    {
      "ASSEMBLY SEAT NO": "46",
      "ASSEMBLY NAME": "Nikol",
      "CANDIDATE NAME": "ASHOK GAJERA",
      "Facebook Profile Link": "https://www.facebook.com/profile.php?id=100086740547819 ",
      "Twitter link": "https://twitter.com/ASHOKGAJERA46 ",
      "Place": "Not Available",
      "Designation": "Not Available",
      "Mobile No.": "Not Available"
    },
    {
      "ASSEMBLY SEAT NO": "47",
      "ASSEMBLY NAME": "Naroda",
      "CANDIDATE NAME": "Omprakash Tiwari",
      "Facebook Profile Link": "Not Available",
      "Twitter link": "Not Available",
      "Place": "Not Available",
      "Designation": "Not Available",
      "Mobile No.": "Not Available"
    },
    {
      "ASSEMBLY SEAT NO": "48",
      "ASSEMBLY NAME": "Thakkarbapa Nagar",
      "CANDIDATE NAME": "Sanjay Mori",
      "Facebook Profile Link": "Not Available",
      "Twitter link": "Not Available",
      "Place": "Not Available",
      "Designation": "Not Available",
      "Mobile No.": "Not Available"
    },
    {
      "ASSEMBLY SEAT NO": "49",
      "ASSEMBLY NAME": "Bapunagar",
      "CANDIDATE NAME": "Rajeshbhai Dixit",
      "Facebook Profile Link": "Not Available",
      "Twitter link": "Not Available",
      "Place": "Not Available",
      "Designation": "Not Available",
      "Mobile No.": "Not Available"
    },
    {
      "ASSEMBLY SEAT NO": "50",
      "ASSEMBLY NAME": "Amraiwadi",
      "CANDIDATE NAME": "BHARATBHAI PATEL",
      "Facebook Profile Link": "https://www.facebook.com/BharatPatelAAP",
      "Twitter link": "https://twitter.com/BharatPatelAAP ",
      "Place": "ahmedabad",
      "Designation": "Not Available",
      "Mobile No.": "9998036275"
    },
    {
      "ASSEMBLY SEAT NO": "51",
      "ASSEMBLY NAME": "Dariapur",
      "CANDIDATE NAME": "Taj Qureshi",
      "Facebook Profile Link": "https://www.facebook.com/taj.qureshi.108",
      "Twitter link": "Not Available",
      "Place": " Ahmedabad",
      "Designation": "दरियापुर विधानसभा संगठन मंत्री",
      "Mobile No.": "Not Available"
    },
    {
      "ASSEMBLY SEAT NO": "52",
      "ASSEMBLY NAME": "Jamalpur-Khadia",
      "CANDIDATE NAME": "Harun Nagori",
      "Facebook Profile Link": "https://www.facebook.com/profile.php?id=100071231454296",
      "Twitter link": "Not Available",
      "Place": "Not Available",
      "Designation": "Not Available",
      "Mobile No.": "Not Available"
    },
    {
      "ASSEMBLY SEAT NO": "53",
      "ASSEMBLY NAME": "Maninagar",
      "CANDIDATE NAME": "Vipul Patel",
      "Facebook Profile Link": "Not Available",
      "Twitter link": "Not Available",
      "Place": "Not Available",
      "Designation": "Not Available",
      "Mobile No.": "Not Available"
    },
    {
      "ASSEMBLY SEAT NO": "54",
      "ASSEMBLY NAME": "Danilimda (SC)",
      "CANDIDATE NAME": "DINESH KAPADIYA",
      "Facebook Profile Link": "https://www.facebook.com/dineshkumarkapadia",
      "Twitter link": "https://twitter.com/DineshKapadia22",
      "Place": "Not Available",
      "Designation": "Not Available",
      "Mobile No.": "8980031068"
    },
    {
      "ASSEMBLY SEAT NO": "55",
      "ASSEMBLY NAME": "Sabarmati",
      "CANDIDATE NAME": "JASVANT THAKOR",
      "Facebook Profile Link": "Not Available",
      "Twitter link": "Not Available",
      "Place": "Not Available",
      "Designation": "Not Available",
      "Mobile No.": "Not Available"
    },
    {
      "ASSEMBLY SEAT NO": "56",
      "ASSEMBLY NAME": "Asarwa (SC)",
      "CANDIDATE NAME": " J J MEWADA",
      "Facebook Profile Link": "https://www.facebook.com/profile.php?id=100067983438535",
      "Twitter link": "Not Available",
      "Place": "Not Available",
      "Designation": "Not Available",
      "Mobile No.": "Not Available"
    },
    {
      "ASSEMBLY SEAT NO": "57",
      "ASSEMBLY NAME": "Daskroi",
      "CANDIDATE NAME": "Kiran Patel",
      "Facebook Profile Link": "https://www.facebook.com/KiranPatelAAP",
      "Twitter link": "https://twitter.com/KiranPatelAAP",
      "Place": "ahmedabad",
      "Designation": "Ahmedabad District Presidant Of AAP",
      "Mobile No.": "099250 31874"
    },
    {
      "ASSEMBLY SEAT NO": "58",
      "ASSEMBLY NAME": "Dholka",
      "CANDIDATE NAME": "Jattuba Gol",
      "Facebook Profile Link": "Not Available",
      "Twitter link": "Not Available",
      "Place": "Not Available",
      "Designation": "Not Available",
      "Mobile No.": "Not Available"
    },
    {
      "ASSEMBLY SEAT NO": "59",
      "ASSEMBLY NAME": "Dhandhuka",
      "CANDIDATE NAME": "Chandu Bamroliya",
      "Facebook Profile Link": "Not Available",
      "Twitter link": "Not Available",
      "Place": "Not Available",
      "Designation": "Not Available",
      "Mobile No.": "Not Available"
    },
    {
      "ASSEMBLY SEAT NO": "60",
      "ASSEMBLY NAME": "Dasada (SC)",
      "CANDIDATE NAME": "Aravind Solanki",
      "Facebook Profile Link": "Not Available",
      "Twitter link": "Not Available",
      "Place": "Not Available",
      "Designation": "Not Available",
      "Mobile No.": "Not Available"
    },
    {
      "ASSEMBLY SEAT NO": "61",
      "ASSEMBLY NAME": "Limdi",
      "CANDIDATE NAME": "Mayur Sakariya",
      "Facebook Profile Link": "Not Available",
      "Twitter link": "Not Available",
      "Place": "Not Available",
      "Designation": "Not Available",
      "Mobile No.": "Not Available"
    },
    {
      "ASSEMBLY SEAT NO": "62",
      "ASSEMBLY NAME": "Wadhwan",
      "CANDIDATE NAME": "HITESH PATEL BANJRANG",
      "Facebook Profile Link": "Not Available",
      "Twitter link": "Not Available",
      "Place": "Not Available",
      "Designation": "Not Available",
      "Mobile No.": "Not Available"
    },
    {
      "ASSEMBLY SEAT NO": "63",
      "ASSEMBLY NAME": "Chotila",
      "CANDIDATE NAME": "RAJU KARPADA",
      "Facebook Profile Link": "https://www.facebook.com/Rajubhaikarpada21",
      "Twitter link": " ",
      "Place": "Not Available",
      "Designation": "Not Available",
      "Mobile No.": "8000080380"
    },
    {
      "ASSEMBLY SEAT NO": "64",
      "ASSEMBLY NAME": "Dhrangadhra",
      "CANDIDATE NAME": "Vagjibhai Patel",
      "Facebook Profile Link": "Not Available",
      "Twitter link": "Not Available",
      "Place": "Not Available",
      "Designation": "Not Available",
      "Mobile No.": "Not Available"
    },
    {
      "ASSEMBLY SEAT NO": "65",
      "ASSEMBLY NAME": "Morbi",
      "CANDIDATE NAME": "PANKAJ RANSARIYA",
      "Facebook Profile Link": "https://www.facebook.com/profile.php?id=100039388947052",
      "Twitter link": "Not Available",
      "Place": "Not Available",
      "Designation": "Not Available",
      "Mobile No.": "9725555555"
    },
    {
      "ASSEMBLY SEAT NO": "66",
      "ASSEMBLY NAME": "Tankara",
      "CANDIDATE NAME": "SANJAY BHATASANA",
      "Facebook Profile Link": "https://www.facebook.com/sanjaypatelmorbiaap",
      "Twitter link": "Not Available",
      "Place": "Not Available",
      "Designation": "Not Available",
      "Mobile No.": "9979648672"
    },
    {
      "ASSEMBLY SEAT NO": "67",
      "ASSEMBLY NAME": "Wankaner",
      "CANDIDATE NAME": "VIKRAM SORANI",
      "Facebook Profile Link": "https://www.facebook.com/vikramsoraniofficial",
      "Twitter link": "Not Available",
      "Place": "Not Available",
      "Designation": "Not Available",
      "Mobile No.": "9998491986"
    },
    {
      "ASSEMBLY SEAT NO": "68",
      "ASSEMBLY NAME": "Rajkot East",
      "CANDIDATE NAME": "Rahul Bhuva",
      "Facebook Profile Link": "https://www.facebook.com/rahuljbhuva",
      "Twitter link": "Not Available",
      "Place": "Not Available",
      "Designation": "Not Available",
      "Mobile No.": "Not Available"
    },
    {
      "ASSEMBLY SEAT NO": "69",
      "ASSEMBLY NAME": "Rajkot West",
      "CANDIDATE NAME": "Dinesh Joshi",
      "Facebook Profile Link": "Not Available",
      "Twitter link": "Not Available",
      "Place": "Not Available",
      "Designation": "Not Available",
      "Mobile No.": "Not Available"
    },
    {
      "ASSEMBLY SEAT NO": "70",
      "ASSEMBLY NAME": "Rajkot South",
      "CANDIDATE NAME": "SHIVLAL BARASIYA",
      "Facebook Profile Link": "https://www.facebook.com/Aapshivlalpatel/",
      "Twitter link": "Not Available",
      "Place": "Not Available",
      "Designation": "Not Available",
      "Mobile No.": "9825079022"
    },
    {
      "ASSEMBLY SEAT NO": "71",
      "ASSEMBLY NAME": "Rajkot Rural (SC)",
      "CANDIDATE NAME": "VSHRAM SAGATHIYA",
      "Facebook Profile Link": "https://www.facebook.com/vashramsagthiya ",
      "Twitter link": "Not Available",
      "Place": "Not Available",
      "Designation": "Not Available",
      "Mobile No.": "Not Available"
    },
    {
      "ASSEMBLY SEAT NO": "72",
      "ASSEMBLY NAME": "Jasdan",
      "CANDIDATE NAME": "Tejas Gazipara",
      "Facebook Profile Link": "Not Available",
      "Twitter link": "Not Available",
      "Place": "Not Available",
      "Designation": "Not Available",
      "Mobile No.": "Not Available"
    },
    {
      "ASSEMBLY SEAT NO": "73",
      "ASSEMBLY NAME": "Gondal",
      "CANDIDATE NAME": "NIMISHA KHUNT",
      "Facebook Profile Link": "https://www.facebook.com/Nimishakhunt13/",
      "Twitter link": "Not Available",
      "Place": "Not Available",
      "Designation": "Not Available",
      "Mobile No.": "9393940000"
    },
    {
      "ASSEMBLY SEAT NO": "74",
      "ASSEMBLY NAME": "Jetpur",
      "CANDIDATE NAME": "Rohit bhuva",
      "Facebook Profile Link": "Not Available",
      "Twitter link": "Not Available",
      "Place": "Not Available",
      "Designation": "Not Available",
      "Mobile No.": "Not Available"
    },
    {
      "ASSEMBLY SEAT NO": "75",
      "ASSEMBLY NAME": "Dhoraji",
      "CANDIDATE NAME": "VIPUL SAKHIYA",
      "Facebook Profile Link": "https://www.facebook.com/profile.php?id=100086760604961",
      "Twitter link": "Not Available",
      "Place": "Not Available",
      "Designation": "Not Available",
      "Mobile No.": "9173638686"
    },
    {
      "ASSEMBLY SEAT NO": "76",
      "ASSEMBLY NAME": "Kalavad (SC)",
      "CANDIDATE NAME": "DR JIGNESH SOLANKI",
      "Facebook Profile Link": "https://www.facebook.com/jignesh.solanki.777",
      "Twitter link": "Not Available",
      "Place": "Not Available",
      "Designation": "Not Available",
      "Mobile No.": "9662275112"
    },
    {
      "ASSEMBLY SEAT NO": "77",
      "ASSEMBLY NAME": "Jamnagar Rural",
      "CANDIDATE NAME": "PRAKASH DONGA",
      "Facebook Profile Link": "https://www.facebook.com/AAPJAM",
      "Twitter link": "Not Available",
      "Place": "Not Available",
      "Designation": "Not Available",
      "Mobile No.": "9228667788"
    },
    {
      "ASSEMBLY SEAT NO": "78",
      "ASSEMBLY NAME": "Jamnagar North",
      "CANDIDATE NAME": "KARASAN KARMUR",
      "Facebook Profile Link": "https://www.facebook.com/aapkarshankarmur",
      "Twitter link": " ",
      "Place": "Not Available",
      "Designation": "Not Available",
      "Mobile No.": "8504811111"
    },
    {
      "ASSEMBLY SEAT NO": "79",
      "ASSEMBLY NAME": "Jamnagar South",
      "CANDIDATE NAME": "Vishal Tyagi",
      "Facebook Profile Link": "https://www.facebook.com/profile.php?id=100082712657929",
      "Twitter link": "https://twitter.com/AapGujaratState",
      "Place": "Jamnagar ",
      "Designation": "AAP GUJARAT STATE YOUTH WISE PRESIDENT",
      "Mobile No.": "Not Available"
    },
    {
      "ASSEMBLY SEAT NO": "80",
      "ASSEMBLY NAME": "Jamjodhpur",
      "CANDIDATE NAME": "Hemant Khava",
      "Facebook Profile Link": "https://www.facebook.com/hemantkhava",
      "Twitter link": "Not Available",
      "Place": "Jamnagar ",
      "Designation": "Not Available",
      "Mobile No.": "2882670001"
    },
    {
      "ASSEMBLY SEAT NO": "81",
      "ASSEMBLY NAME": "Khambhalia",
      "CANDIDATE NAME": "Isudan Gadhvi",
      "Facebook Profile Link": "https://www.facebook.com/isudangadhviofficial",
      "Twitter link": "https://twitter.com/isudan_gadhvi",
      "Place": "Not Available",
      "Designation": "National Joint General Secretary",
      "Mobile No.": "Not Available"
    },
    {
      "ASSEMBLY SEAT NO": "82",
      "ASSEMBLY NAME": "Dwarka",
      "CANDIDATE NAME": "Lakhman Nakum",
      "Facebook Profile Link": "Not Available",
      "Twitter link": "Not Available",
      "Place": "Not Available",
      "Designation": "Not Available",
      "Mobile No.": "Not Available"
    },
    {
      "ASSEMBLY SEAT NO": "83",
      "ASSEMBLY NAME": "Porbandar",
      "CANDIDATE NAME": "JIVAN JUNGI",
      "Facebook Profile Link": "https://www.facebook.com/shreekharva.chintansamiti",
      "Twitter link": "Not Available",
      "Place": "Not Available",
      "Designation": "Not Available",
      "Mobile No.": "Not Available"
    },
    {
      "ASSEMBLY SEAT NO": "84",
      "ASSEMBLY NAME": "Kutiyana",
      "CANDIDATE NAME": "Bhimabhai Danabhai Makavana",
      "Facebook Profile Link": "Not Available",
      "Twitter link": "Not Available",
      "Place": "Not Available",
      "Designation": "Not Available",
      "Mobile No.": "Not Available"
    },
    {
      "ASSEMBLY SEAT NO": "85",
      "ASSEMBLY NAME": "Manavadar",
      "CANDIDATE NAME": "Karsanbapu Bhadrak",
      "Facebook Profile Link": "Not Available",
      "Twitter link": "Not Available",
      "Place": "Not Available",
      "Designation": "Not Available",
      "Mobile No.": "Not Available"
    },
    {
      "ASSEMBLY SEAT NO": "86",
      "ASSEMBLY NAME": "Junagadh",
      "CANDIDATE NAME": "CHETAN GAJERA",
      "Facebook Profile Link": "https://www.facebook.com/chetan.gajera.10 ",
      "Twitter link": "https://twitter.com/chetangajera22 ",
      "Place": "Junagadh",
      "Designation": "Not Available",
      "Mobile No.": "9824431152"
    },
    {
      "ASSEMBLY SEAT NO": "87",
      "ASSEMBLY NAME": "Visavadar",
      "CANDIDATE NAME": "BHUPAT BHAYANI",
      "Facebook Profile Link": "https://www.facebook.com/profile.php?id=100006037934876",
      "Twitter link": "Not Available",
      "Place": "Not Available",
      "Designation": "Not Available",
      "Mobile No.": "Not Available"
    },
    {
      "ASSEMBLY SEAT NO": "88",
      "ASSEMBLY NAME": "Keshod",
      "CANDIDATE NAME": "RAMJIBHAI CHUDASAMA",
      "Facebook Profile Link": "https://www.facebook.com/Ramjibhaichdasama/ ",
      "Twitter link": "Not Available",
      "Place": "Not Available",
      "Designation": "Not Available",
      "Mobile No.": "9879432737"
    },
    {
      "ASSEMBLY SEAT NO": "89",
      "ASSEMBLY NAME": "Mangrol (Junagadh)",
      "CANDIDATE NAME": "PIYUSH PARMAR",
      "Facebook Profile Link": "https://www.facebook.com/piyushparmaraap",
      "Twitter link": "Not Available",
      "Place": "Not Available",
      "Designation": "Not Available",
      "Mobile No.": "9924002391"
    },
    {
      "ASSEMBLY SEAT NO": "90",
      "ASSEMBLY NAME": "Somnath",
      "CANDIDATE NAME": "JAGMAL VALA",
      "Facebook Profile Link": "https://www.facebook.com/JagmalVala",
      "Twitter link": "https://twitter.com/jagmalbhaivala",
      "Place": "Not Available",
      "Designation": "Not Available",
      "Mobile No.": "Not Available"
    },
    {
      "ASSEMBLY SEAT NO": "91",
      "ASSEMBLY NAME": "Talala",
      "CANDIDATE NAME": "Devender Solanki",
      "Facebook Profile Link": "Not Available",
      "Twitter link": "Not Available",
      "Place": "Not Available",
      "Designation": "Not Available",
      "Mobile No.": "Not Available"
    },
    {
      "ASSEMBLY SEAT NO": "92",
      "ASSEMBLY NAME": "Kodinar (SC)",
      "CANDIDATE NAME": "VALJIBHAI MAKWANA",
      "Facebook Profile Link": "Not Available",
      "Twitter link": "Not Available",
      "Place": "Not Available",
      "Designation": "Not Available",
      "Mobile No.": "Not Available"
    },
    {
      "ASSEMBLY SEAT NO": "93",
      "ASSEMBLY NAME": "Una",
      "CANDIDATE NAME": "Sejalben Khunt",
      "Facebook Profile Link": "Not Available",
      "Twitter link": "Not Available",
      "Place": "Not Available",
      "Designation": "Not Available",
      "Mobile No.": "Not Available"
    },
    {
      "ASSEMBLY SEAT NO": "94",
      "ASSEMBLY NAME": "Dhari",
      "CANDIDATE NAME": "Kantibhai Satasiya",
      "Facebook Profile Link": "https://www.facebook.com/kantibhai.satasiya",
      "Twitter link": "https://twitter.com/Kantibhaisatas",
      "Place": "Bagasara",
      "Designation": "એ.પી.એમ.સી. પુર્વ ચેરમેન બગસરા",
      "Mobile No.": "Not Available"
    },
    {
      "ASSEMBLY SEAT NO": "95",
      "ASSEMBLY NAME": "Amreli",
      "CANDIDATE NAME": "Ravi Dhanani",
      "Facebook Profile Link": "Not Available",
      "Twitter link": "Not Available",
      "Place": "Not Available",
      "Designation": "Not Available",
      "Mobile No.": "Not Available"
    },
    {
      "ASSEMBLY SEAT NO": "96",
      "ASSEMBLY NAME": "Lathi",
      "CANDIDATE NAME": "Jaysukh Detroja",
      "Facebook Profile Link": "Not Available",
      "Twitter link": "Not Available",
      "Place": "Not Available",
      "Designation": "Not Available",
      "Mobile No.": "Not Available"
    },
    {
      "ASSEMBLY SEAT NO": "97",
      "ASSEMBLY NAME": "Savarkundla",
      "CANDIDATE NAME": "Bharat Nakrani",
      "Facebook Profile Link": "https://www.facebook.com/nakrani.bharat.12",
      "Twitter link": "https://twitter.com/BharatNakrani7",
      "Place": "Savarkundla",
      "Designation": "તાલુકા પ્રમુખ સાવરકુંડલા",
      "Mobile No.": "Not Available"
    },
    {
      "ASSEMBLY SEAT NO": "98",
      "ASSEMBLY NAME": "Rajula",
      "CANDIDATE NAME": "Bharat Baldania",
      "Facebook Profile Link": "Not Available",
      "Twitter link": "Not Available",
      "Place": "Not Available",
      "Designation": "Not Available",
      "Mobile No.": "Not Available"
    },
    {
      "ASSEMBLY SEAT NO": "99",
      "ASSEMBLY NAME": "Mahuva (Bhavnagar)",
      "CANDIDATE NAME": "Ashok Joliya",
      "Facebook Profile Link": "Not Available",
      "Twitter link": "Not Available",
      "Place": "Not Available",
      "Designation": "Not Available",
      "Mobile No.": "Not Available"
    },
    {
      "ASSEMBLY SEAT NO": "100",
      "ASSEMBLY NAME": "Talaja",
      "CANDIDATE NAME": "LABHUBEN NARSHIBHAI CHAUHAN",
      "Facebook Profile Link": "https://www.facebook.com/narshibhai.chauhan",
      "Twitter link": "Not Available",
      "Place": "Bhavnagar",
      "Designation": "Not Available",
      "Mobile No.": "Not Available"
    },
    {
      "ASSEMBLY SEAT NO": "101",
      "ASSEMBLY NAME": "Gariadhar",
      "CANDIDATE NAME": "SUDHIR VAGHANI",
      "Facebook Profile Link": "https://www.facebook.com/profile.php?id=100063754478316",
      "Twitter link": "Not Available",
      "Place": "Not Available",
      "Designation": "Not Available",
      "Mobile No.": "Not Available"
    },
    {
      "ASSEMBLY SEAT NO": "102",
      "ASSEMBLY NAME": "Palitana",
      "CANDIDATE NAME": "Dr ZP Kheni",
      "Facebook Profile Link": "https://www.facebook.com/hiren.kheni.77",
      "Twitter link": "Not Available",
      "Place": "Not Available",
      "Designation": "Not Available",
      "Mobile No.": "9712316009"
    },
    {
      "ASSEMBLY SEAT NO": "103",
      "ASSEMBLY NAME": "Bhavnagar Rural",
      "CANDIDATE NAME": "Khumansinh Gohil",
      "Facebook Profile Link": "https://www.facebook.com/randhvir.gohil",
      "Twitter link": "Not Available",
      "Place": " Bhavnagar",
      "Designation": "Not Available",
      "Mobile No.": "9328727070"
    },
    {
      "ASSEMBLY SEAT NO": "104",
      "ASSEMBLY NAME": "Bhavnagar East",
      "CANDIDATE NAME": "HAMIRBHAI RATHOD",
      "Facebook Profile Link": "https://www.facebook.com/RathodHamir127/",
      "Twitter link": "https://twitter.com/hamirrathod127",
      "Place": "Bhavnagar",
      "Designation": "104 Bhavnagar East Assembly Constituency Candidate",
      "Mobile No.": "9081999967"
    },
    {
      "ASSEMBLY SEAT NO": "105",
      "ASSEMBLY NAME": "Bhavnagar West",
      "CANDIDATE NAME": "RAJUBHAI SOLANKI",
      "Facebook Profile Link": "https://www.facebook.com/Adhyaksh.KoliRajuSolanki",
      "Twitter link": "https://twitter.com/KoliRajuSolanki",
      "Place": "Not Available",
      "Designation": "Not Available",
      "Mobile No.": "7069441611"
    },
    {
      "ASSEMBLY SEAT NO": "106",
      "ASSEMBLY NAME": "Gadhada (SC)",
      "CANDIDATE NAME": "Ramesh Parmar",
      "Facebook Profile Link": "Not Available",
      "Twitter link": "Not Available",
      "Place": "Not Available",
      "Designation": "Not Available",
      "Mobile No.": "Not Available"
    },
    {
      "ASSEMBLY SEAT NO": "107",
      "ASSEMBLY NAME": "Botad",
      "CANDIDATE NAME": "Umesh Makawana",
      "Facebook Profile Link": "https://www.facebook.com/umakwana3",
      "Twitter link": "Not Available",
      "Place": "Not Available",
      "Designation": "પ્રદેશ પ્રવકતા &ભાવનગર લોકસભા પ્રમુખ આપ,",
      "Mobile No.": "9898989693"
    },
    {
      "ASSEMBLY SEAT NO": "108",
      "ASSEMBLY NAME": "Khambhat",
      "CANDIDATE NAME": "Arun Gohil",
      "Facebook Profile Link": "https://www.facebook.com/profile.php?id=100074619467102",
      "Twitter link": "https://twitter.com/ArunGohilSP",
      "Place": "Khambhat",
      "Designation": "Not Available",
      "Mobile No.": "Not Available"
    },
    {
      "ASSEMBLY SEAT NO": "109",
      "ASSEMBLY NAME": "Borsad",
      "CANDIDATE NAME": "MANISH PATEL",
      "Facebook Profile Link": "Not Available",
      "Twitter link": "Not Available",
      "Place": "Not Available",
      "Designation": "Not Available",
      "Mobile No.": "Not Available"
    },
    {
      "ASSEMBLY SEAT NO": "110",
      "ASSEMBLY NAME": "Anklav",
      "CANDIDATE NAME": "GAJENDRASINH",
      "Facebook Profile Link": "https://www.facebook.com/gajendrasinh.raj.73",
      "Twitter link": "Not Available",
      "Place": "Not Available",
      "Designation": "Not Available",
      "Mobile No.": "Not Available"
    },
    {
      "ASSEMBLY SEAT NO": "111",
      "ASSEMBLY NAME": "Umreth",
      "CANDIDATE NAME": "AMRISH PATEL",
      "Facebook Profile Link": "Not Available",
      "Twitter link": "Not Available",
      "Place": "Not Available",
      "Designation": "Not Available",
      "Mobile No.": "Not Available"
    },
    {
      "ASSEMBLY SEAT NO": "112",
      "ASSEMBLY NAME": "Anand",
      "CANDIDATE NAME": "Girish Shandilya",
      "Facebook Profile Link": "Not Available",
      "Twitter link": "Not Available",
      "Place": "Not Available",
      "Designation": "Not Available",
      "Mobile No.": "Not Available"
    },
    {
      "ASSEMBLY SEAT NO": "113",
      "ASSEMBLY NAME": "Petlad",
      "CANDIDATE NAME": "Arjun Bharvad",
      "Facebook Profile Link": "Not Available",
      "Twitter link": "Not Available",
      "Place": "Not Available",
      "Designation": "Not Available",
      "Mobile No.": "Not Available"
    },
    {
      "ASSEMBLY SEAT NO": "114",
      "ASSEMBLY NAME": "Sojitra",
      "CANDIDATE NAME": "Manubhai Thakor",
      "Facebook Profile Link": "Not Available",
      "Twitter link": "Not Available",
      "Place": "Not Available",
      "Designation": "Not Available",
      "Mobile No.": "Not Available"
    },
    {
      "ASSEMBLY SEAT NO": "115",
      "ASSEMBLY NAME": "Matar",
      "CANDIDATE NAME": "Lalaji Parmar",
      "Facebook Profile Link": "Not Available",
      "Twitter link": "Not Available",
      "Place": "Not Available",
      "Designation": "Not Available",
      "Mobile No.": "Not Available"
    },
    {
      "ASSEMBLY SEAT NO": "116",
      "ASSEMBLY NAME": "Nadiad",
      "CANDIDATE NAME": "Harshad vaghela",
      "Facebook Profile Link": "Not Available",
      "Twitter link": "Not Available",
      "Place": "Not Available",
      "Designation": "Not Available",
      "Mobile No.": "Not Available"
    },
    {
      "ASSEMBLY SEAT NO": "117",
      "ASSEMBLY NAME": "Mehmedabad",
      "CANDIDATE NAME": "PARMODBHAI CHAUHAN",
      "Facebook Profile Link": "Not Available",
      "Twitter link": "Not Available",
      "Place": "Not Available",
      "Designation": "Not Available",
      "Mobile No.": "Not Available"
    },
    {
      "ASSEMBLY SEAT NO": "118",
      "ASSEMBLY NAME": "Mahudha",
      "CANDIDATE NAME": "RAVJIBHAI SOMABHAI VAGHELA",
      "Facebook Profile Link": "https://www.facebook.com/ravjibhai.vaghela.963",
      "Twitter link": "Not Available",
      "Place": "Not Available",
      "Designation": "Not Available",
      "Mobile No.": "Not Available"
    },
    {
      "ASSEMBLY SEAT NO": "119",
      "ASSEMBLY NAME": "Thasra",
      "CANDIDATE NAME": "NATVARSINH RATHOD",
      "Facebook Profile Link": "https://www.facebook.com/rathodnatvarsinh.rathodnatvarsinh.3",
      "Twitter link": "Not Available",
      "Place": "Not Available",
      "Designation": "Not Available",
      "Mobile No.": "7359686101"
    },
    {
      "ASSEMBLY SEAT NO": "120",
      "ASSEMBLY NAME": "Kapadvanj",
      "CANDIDATE NAME": "MANUBHAI PATEL",
      "Facebook Profile Link": "Not Available",
      "Twitter link": "Not Available",
      "Place": "Not Available",
      "Designation": "Not Available",
      "Mobile No.": "Not Available"
    },
    {
      "ASSEMBLY SEAT NO": "121",
      "ASSEMBLY NAME": "Balasinor",
      "CANDIDATE NAME": "UDEYSINH CHAUHAN",
      "Facebook Profile Link": "https://www.facebook.com/profile.php?id=100086985090732",
      "Twitter link": "Not Available",
      "Place": "Not Available",
      "Designation": "Not Available",
      "Mobile No.": "Not Available"
    },
    {
      "ASSEMBLY SEAT NO": "122",
      "ASSEMBLY NAME": "Lunawada",
      "CANDIDATE NAME": "NATVARSINH SOLANKI",
      "Facebook Profile Link": "https://www.facebook.com/profile.php?id=100087104841210",
      "Twitter link": "Not Available",
      "Place": "Not Available",
      "Designation": "Not Available",
      "Mobile No.": "Not Available"
    },
    {
      "ASSEMBLY SEAT NO": "123",
      "ASSEMBLY NAME": "Santrampur (ST)",
      "CANDIDATE NAME": "PARVAT VAGODIYA FAUJI",
      "Facebook Profile Link": "https://www.facebook.com/parvatsingh.vagadia",
      "Twitter link": "Not Available",
      "Place": "Not Available",
      "Designation": "Not Available",
      "Mobile No.": "Not Available"
    },
    {
      "ASSEMBLY SEAT NO": "124",
      "ASSEMBLY NAME": "Shehra",
      "CANDIDATE NAME": "TAKHATSINH SOLANKI",
      "Facebook Profile Link": "https://www.facebook.com/takhatsinh.solanki.31",
      "Twitter link": "Not Available",
      "Place": "Not Available",
      "Designation": "Not Available",
      "Mobile No.": "9825925892"
    },
    {
      "ASSEMBLY SEAT NO": "125",
      "ASSEMBLY NAME": "Morva Hadaf (ST)",
      "CANDIDATE NAME": "BANABHAI DAMOR",
      "Facebook Profile Link": "https://www.facebook.com/damor.bhanabhai.5",
      "Twitter link": "Not Available",
      "Place": "Not Available",
      "Designation": "Not Available",
      "Mobile No.": "7990775372"
    },
    {
      "ASSEMBLY SEAT NO": "126",
      "ASSEMBLY NAME": "Godhra",
      "CANDIDATE NAME": "Rajesh Patel Raju",
      "Facebook Profile Link": "Not Available",
      "Twitter link": "Not Available",
      "Place": "Not Available",
      "Designation": "Not Available",
      "Mobile No.": "Not Available"
    },
    {
      "ASSEMBLY SEAT NO": "127",
      "ASSEMBLY NAME": "Kalol (Panchmahal)",
      "CANDIDATE NAME": "DINESH BARIYA",
      "Facebook Profile Link": "https://www.facebook.com/Dinesh-Baria-Panchmahal-AAP-Gujarat-103476765750009",
      "Twitter link": "Not Available",
      "Place": "Not Available",
      "Designation": "Not Available",
      "Mobile No.": "9099698968"
    },
    {
      "ASSEMBLY SEAT NO": "128",
      "ASSEMBLY NAME": "Halol",
      "CANDIDATE NAME": "Bharat Rathva",
      "Facebook Profile Link": "Not Available",
      "Twitter link": "Not Available",
      "Place": "Not Available",
      "Designation": "Not Available",
      "Mobile No.": "Not Available"
    },
    {
      "ASSEMBLY SEAT NO": "129",
      "ASSEMBLY NAME": "Fatepura (ST)",
      "CANDIDATE NAME": "Govind Parmar",
      "Facebook Profile Link": "Not Available",
      "Twitter link": "Not Available",
      "Place": "Not Available",
      "Designation": "Not Available",
      "Mobile No.": "Not Available"
    },
    {
      "ASSEMBLY SEAT NO": "130",
      "ASSEMBLY NAME": "Jhalod (ST)",
      "CANDIDATE NAME": "ANIL GHARASIYA",
      "Facebook Profile Link": "https://www.facebook.com/profile.php?id=100087020826970",
      "Twitter link": "Not Available",
      "Place": "Not Available",
      "Designation": "Not Available",
      "Mobile No.": "9904521781"
    },
    {
      "ASSEMBLY SEAT NO": "131",
      "ASSEMBLY NAME": "Limkheda (ST)",
      "CANDIDATE NAME": "Naresh Punabhai Bariya",
      "Facebook Profile Link": "Not Available",
      "Twitter link": "Not Available",
      "Place": "Not Available",
      "Designation": "Not Available",
      "Mobile No.": "Not Available"
    },
    {
      "ASSEMBLY SEAT NO": "132",
      "ASSEMBLY NAME": "Dahod (ST)",
      "CANDIDATE NAME": "PROF DINESH MUNIYA",
      "Facebook Profile Link": "https://www.facebook.com/db.muniya",
      "Twitter link": "https://twitter.com/AAPKaProfDinesh",
      "Place": "Not Available",
      "Designation": "Not Available",
      "Mobile No.": "Not Available"
    },
    {
      "ASSEMBLY SEAT NO": "133",
      "ASSEMBLY NAME": "Garbada (ST)",
      "CANDIDATE NAME": "SHAILESHBHAI DAMOR",
      "Facebook Profile Link": "Not Available",
      "Twitter link": "Not Available",
      "Place": "Not Available",
      "Designation": "Not Available",
      "Mobile No.": "Not Available"
    },
    {
      "ASSEMBLY SEAT NO": "134",
      "ASSEMBLY NAME": "Devgadhbaria",
      "CANDIDATE NAME": "BHARAT VAKHALA",
      "Facebook Profile Link": "https://www.facebook.com/Vakhla.Bharatsinh",
      "Twitter link": "Not Available",
      "Place": "Not Available",
      "Designation": "Not Available",
      "Mobile No.": "9925441595"
    },
    {
      "ASSEMBLY SEAT NO": "135",
      "ASSEMBLY NAME": "Savli",
      "CANDIDATE NAME": "VIJAY CHAVDA",
      "Facebook Profile Link": "https://www.facebook.com/profile.php?id=100087309136630",
      "Twitter link": "Not Available",
      "Place": "Not Available",
      "Designation": "Not Available",
      "Mobile No.": "Not Available"
    },
    {
      "ASSEMBLY SEAT NO": "136",
      "ASSEMBLY NAME": "Vaghodia",
      "CANDIDATE NAME": "Gautam Rajput",
      "Facebook Profile Link": "Not Available",
      "Twitter link": "Not Available",
      "Place": "Not Available",
      "Designation": "Not Available",
      "Mobile No.": "Not Available"
    },
    {
      "ASSEMBLY SEAT NO": "137",
      "ASSEMBLY NAME": "Chhota Udaipur (ST)",
      "CANDIDATE NAME": "ARJUN RATHAVA",
      "Facebook Profile Link": "https://www.facebook.com/aaparjunrathwa",
      "Twitter link": "https://twitter.com/aaparjunrathva",
      "Place": "Not Available",
      "Designation": "Not Available",
      "Mobile No.": "Not Available"
    },
    {
      "ASSEMBLY SEAT NO": "138",
      "ASSEMBLY NAME": "Jetpur (ST)",
      "CANDIDATE NAME": "Radhika Rathva",
      "Facebook Profile Link": "Not Available",
      "Twitter link": "Not Available",
      "Place": "Not Available",
      "Designation": "Not Available",
      "Mobile No.": "Not Available"
    },
    {
      "ASSEMBLY SEAT NO": "139",
      "ASSEMBLY NAME": "Sankheda (ST)",
      "CANDIDATE NAME": "RANJAN TADVI",
      "Facebook Profile Link": "https://www.facebook.com/ranjanbhai.tadavi",
      "Twitter link": "Not Available",
      "Place": "Not Available",
      "Designation": "Not Available",
      "Mobile No.": "Not Available"
    },
    {
      "ASSEMBLY SEAT NO": "140",
      "ASSEMBLY NAME": "Dabhoi",
      "CANDIDATE NAME": "Ajit Thakor",
      "Facebook Profile Link": "Not Available",
      "Twitter link": "Not Available",
      "Place": "Not Available",
      "Designation": "Not Available",
      "Mobile No.": "Not Available"
    },
    {
      "ASSEMBLY SEAT NO": "141",
      "ASSEMBLY NAME": "Vadodara City (SC)",
      "CANDIDATE NAME": "Adv Jigar Solanki",
      "Facebook Profile Link": "https://www.facebook.com/jigarsolankiaap",
      "Twitter link": "https://twitter.com/Jigarsolanki22",
      "Place": "Vododara",
      "Designation": "Not Available",
      "Mobile No.": "Not Available"
    },
    {
      "ASSEMBLY SEAT NO": "142",
      "ASSEMBLY NAME": "Sayajigunj",
      "CANDIDATE NAME": "Swejal Vyas",
      "Facebook Profile Link": "Not Available",
      "Twitter link": "Not Available",
      "Place": "Not Available",
      "Designation": "Not Available",
      "Mobile No.": "Not Available"
    },
    {
      "ASSEMBLY SEAT NO": "143",
      "ASSEMBLY NAME": "Akota",
      "CANDIDATE NAME": "Shashank khare",
      "Facebook Profile Link": "Not Available",
      "Twitter link": "Not Available",
      "Place": "Not Available",
      "Designation": "Not Available",
      "Mobile No.": "Not Available"
    },
    {
      "ASSEMBLY SEAT NO": "144",
      "ASSEMBLY NAME": "Raopura",
      "CANDIDATE NAME": "Hiren Sirke",
      "Facebook Profile Link": "Not Available",
      "Twitter link": "Not Available",
      "Place": "Not Available",
      "Designation": "Not Available",
      "Mobile No.": "Not Available"
    },
    {
      "ASSEMBLY SEAT NO": "145",
      "ASSEMBLY NAME": "Manjalpur",
      "CANDIDATE NAME": "VIRAL PANCHAL",
      "Facebook Profile Link": "https://www.facebook.com/viral.panchal.94043",
      "Twitter link": "Not Available",
      "Place": "Not Available",
      "Designation": "Not Available",
      "Mobile No.": "8866039830"
    },
    {
      "ASSEMBLY SEAT NO": "146",
      "ASSEMBLY NAME": "Padra",
      "CANDIDATE NAME": "Jaydeepsinh Chauhan",
      "Facebook Profile Link": "https://www.facebook.com/jaydeepsinh11",
      "Twitter link": "Not Available",
      "Place": "Vadodara",
      "Designation": "Politician",
      "Mobile No.": "099255 59642"
    },
    {
      "ASSEMBLY SEAT NO": "147",
      "ASSEMBLY NAME": "Karjan",
      "CANDIDATE NAME": "Paresh Patel",
      "Facebook Profile Link": "Not Available",
      "Twitter link": "Not Available",
      "Place": "Not Available",
      "Designation": "Not Available",
      "Mobile No.": "Not Available"
    },
    {
      "ASSEMBLY SEAT NO": "148",
      "ASSEMBLY NAME": "Nandod (ST)",
      "CANDIDATE NAME": "DR PRAFUL VASAVA",
      "Facebook Profile Link": "https://www.facebook.com/praful.vasava",
      "Twitter link": "https://twitter.com/PrafulVsv",
      "Place": "Not Available",
      "Designation": "Not Available",
      "Mobile No.": "9725039210"
    },
    {
      "ASSEMBLY SEAT NO": "149",
      "ASSEMBLY NAME": "Dediapada (ST)",
      "CANDIDATE NAME": "CHAITAR VASAVA",
      "Facebook Profile Link": "https://www.facebook.com/profile.php?id=100086249456138",
      "Twitter link": "Not Available",
      "Place": "Not Available",
      "Designation": "Not Available",
      "Mobile No.": "Not Available"
    },
    {
      "ASSEMBLY SEAT NO": "150",
      "ASSEMBLY NAME": "Jambusar",
      "CANDIDATE NAME": "sajid Rehan",
      "Facebook Profile Link": "Not Available",
      "Twitter link": "Not Available",
      "Place": "Not Available",
      "Designation": "Not Available",
      "Mobile No.": "Not Available"
    },
    {
      "ASSEMBLY SEAT NO": "151",
      "ASSEMBLY NAME": "Vagra",
      "CANDIDATE NAME": "Jayraj Singh",
      "Facebook Profile Link": "Not Available",
      "Twitter link": "Not Available",
      "Place": "Not Available",
      "Designation": "Not Available",
      "Mobile No.": "Not Available"
    },
    {
      "ASSEMBLY SEAT NO": "152",
      "ASSEMBLY NAME": "Jhagadia (ST)",
      "CANDIDATE NAME": "Urmila Bhagat",
      "Facebook Profile Link": "Not Available",
      "Twitter link": "Not Available",
      "Place": "Not Available",
      "Designation": "Not Available",
      "Mobile No.": "Not Available"
    },
    {
      "ASSEMBLY SEAT NO": "153",
      "ASSEMBLY NAME": "Bharuch",
      "CANDIDATE NAME": "manahar Parmar",
      "Facebook Profile Link": "Not Available",
      "Twitter link": "Not Available",
      "Place": "Not Available",
      "Designation": "Not Available",
      "Mobile No.": "Not Available"
    },
    {
      "ASSEMBLY SEAT NO": "154",
      "ASSEMBLY NAME": "Ankleshwar",
      "CANDIDATE NAME": "Ankur Patel",
      "Facebook Profile Link": "https://www.facebook.com/ANKUR-PATEL-110242535041252/?ref=page_internal",
      "Twitter link": "Not Available",
      "Place": "Not Available",
      "Designation": "Politician",
      "Mobile No.": "+91 99094 11291"
    },
    {
      "ASSEMBLY SEAT NO": "155",
      "ASSEMBLY NAME": "Olapad",
      "CANDIDATE NAME": "Dharmik malaviya",
      "Facebook Profile Link": "https://www.facebook.com/dharmikmalaviya.official",
      "Twitter link": "https://twitter.com/Dharmikmalaviya",
      "Place": "Not Available",
      "Designation": "Social youth leader",
      "Mobile No.": "098251 39251"
    },
    {
      "ASSEMBLY SEAT NO": "156",
      "ASSEMBLY NAME": "Mangrol (Surat)",
      "CANDIDATE NAME": "SNEHAL VASAVA",
      "Facebook Profile Link": "https://www.facebook.com/snehalvasava.wplaner",
      "Twitter link": "Not Available",
      "Place": "Not Available",
      "Designation": "Not Available",
      "Mobile No.": "9638363484"
    },
    {
      "ASSEMBLY SEAT NO": "157",
      "ASSEMBLY NAME": "Mandvi (Surat)",
      "CANDIDATE NAME": "SAYNABEN GAMIT",
      "Facebook Profile Link": "https://www.facebook.com/profile.php?id=100083123861658",
      "Twitter link": "https://twitter.com/saynaben",
      "Place": "Not Available",
      "Designation": "Not Available",
      "Mobile No.": "Not Available"
    },
    {
      "ASSEMBLY SEAT NO": "158",
      "ASSEMBLY NAME": "Kamrej",
      "CANDIDATE NAME": "RAM DHADUK",
      "Facebook Profile Link": "https://www.facebook.com/ramdhadukofficial/ ",
      "Twitter link": "https://twitter.com/ramdhaduk",
      "Place": "Not Available",
      "Designation": "Not Available",
      "Mobile No.": "9879585646"
    },
    {
      "ASSEMBLY SEAT NO": "159",
      "ASSEMBLY NAME": "Surat East",
      "CANDIDATE NAME": "Kanchan Jariwala",
      "Facebook Profile Link": "https://www.facebook.com/kanchanlal.form.veera.kichan",
      "Twitter link": "Not Available",
      "Place": " Surat",
      "Designation": "Works at Media inquire",
      "Mobile No.": "Not Available"
    },
    {
      "ASSEMBLY SEAT NO": "160",
      "ASSEMBLY NAME": "Surat North",
      "CANDIDATE NAME": "MAHENDRA NAVADIYA",
      "Facebook Profile Link": "https://www.facebook.com/profile.php?id=100064649815880",
      "Twitter link": "Not Available",
      "Place": "Not Available",
      "Designation": "Not Available",
      "Mobile No.": "Not Available"
    },
    {
      "ASSEMBLY SEAT NO": "161",
      "ASSEMBLY NAME": "Varachha Road",
      "CANDIDATE NAME": "Alpesh Kathariya",
      "Facebook Profile Link": "https://www.facebook.com/Alpeshkathiriya.official/",
      "Twitter link": "Not Available",
      "Place": "Not Available",
      "Designation": "Not Available",
      "Mobile No.": "Not Available"
    },
    {
      "ASSEMBLY SEAT NO": "162",
      "ASSEMBLY NAME": "Karanj",
      "CANDIDATE NAME": "Manoj Sorathiya",
      "Facebook Profile Link": "https://www.facebook.com/MSorathiyaofficial",
      "Twitter link": "https://twitter.com/manoj_sorathiya",
      "Place": "Not Available",
      "Designation": "Not Available",
      "Mobile No.": "Not Available"
    },
    {
      "ASSEMBLY SEAT NO": "163",
      "ASSEMBLY NAME": "Limbayat",
      "CANDIDATE NAME": "PANKAJ TAYDE",
      "Facebook Profile Link": "https://www.facebook.com/pankaj.tayade.9404",
      "Twitter link": "https://twitter.com/PankajTayde111",
      "Place": "Not Available",
      "Designation": "Not Available",
      "Mobile No.": "9737763759"
    },
    {
      "ASSEMBLY SEAT NO": "164",
      "ASSEMBLY NAME": "Udhna",
      "CANDIDATE NAME": "Mahendra Patil",
      "Facebook Profile Link": "https://www.facebook.com/mahendrapatil.nana",
      "Twitter link": "Not Available",
      "Place": "Surat",
      "Designation": "Not Available",
      "Mobile No.": "Not Available"
    },
    {
      "ASSEMBLY SEAT NO": "165",
      "ASSEMBLY NAME": "Majura",
      "CANDIDATE NAME": "PVS Sarma",
      "Facebook Profile Link": "https://www.facebook.com/PVS.Sarma.official",
      "Twitter link": "https://twitter.com/pvssarma",
      "Place": "Not Available",
      "Designation": "Not Available",
      "Mobile No.": "9824766666"
    },
    {
      "ASSEMBLY SEAT NO": "166",
      "ASSEMBLY NAME": "Katargam",
      "CANDIDATE NAME": "Gopal Italia",
      "Facebook Profile Link": "https://www.facebook.com/gopalitaliaofficial",
      "Twitter link": "https://twitter.com/Gopal_Italia",
      "Place": "Not Available",
      "Designation": "President, Aam Aadmi Party, Guj.",
      "Mobile No.": "Not Available"
    },
    {
      "ASSEMBLY SEAT NO": "167",
      "ASSEMBLY NAME": "Surat West",
      "CANDIDATE NAME": "Moxesh Sanghvi",
      "Facebook Profile Link": "https://www.facebook.com/AAPkaMOX",
      "Twitter link": "https://twitter.com/moxeshsanghavi2",
      "Place": "Not Available",
      "Designation": "Not Available",
      "Mobile No.": "Not Available"
    },
    {
      "ASSEMBLY SEAT NO": "168",
      "ASSEMBLY NAME": "Choryasi",
      "CANDIDATE NAME": "PRAKASH CONTRACTOR",
      "Facebook Profile Link": "https://m.facebook.com/people/Prakash-contractor/100084565941940/",
      "Twitter link": "https://twitter.com/prakashcontrac4",
      "Place": "Not Available",
      "Designation": "Not Available",
      "Mobile No.": "Not Available"
    },
    {
      "ASSEMBLY SEAT NO": "169",
      "ASSEMBLY NAME": "Bardoli (SC)",
      "CANDIDATE NAME": "RAJENDRA SOLANKI",
      "Facebook Profile Link": "https://www.facebook.com/rajendra.solanki.3760",
      "Twitter link": "Not Available",
      "Place": "Not Available",
      "Designation": "Not Available",
      "Mobile No.": "Not Available"
    },
    {
      "ASSEMBLY SEAT NO": "170",
      "ASSEMBLY NAME": "Mahuva (Surat) (ST)",
      "CANDIDATE NAME": "KUNJAN PATEL DHODIYA",
      "Facebook Profile Link": "https://www.facebook.com/kunjandaytona675",
      "Twitter link": "Not Available",
      "Place": "Not Available",
      "Designation": "Not Available",
      "Mobile No.": "Not Available"
    },
    {
      "ASSEMBLY SEAT NO": "171",
      "ASSEMBLY NAME": "Vyara (ST)",
      "CANDIDATE NAME": "BIPIN CHOUDHARY",
      "Facebook Profile Link": "https://www.facebook.com/bipin.chaudhary.3720",
      "Twitter link": "Not Available",
      "Place": "Not Available",
      "Designation": "Not Available",
      "Mobile No.": "Not Available"
    },
    {
      "ASSEMBLY SEAT NO": "172",
      "ASSEMBLY NAME": "Nizar (ST)",
      "CANDIDATE NAME": "ARVIND GAMIT",
      "Facebook Profile Link": "https://www.facebook.com/profile.php?id=100079975393480",
      "Twitter link": "Not Available",
      "Place": "Not Available",
      "Designation": "Not Available",
      "Mobile No.": "7575069388"
    },
    {
      "ASSEMBLY SEAT NO": "173",
      "ASSEMBLY NAME": "Dang",
      "CANDIDATE NAME": "ADV SUNIL GAMIT",
      "Facebook Profile Link": "https://www.facebook.com/sunil.gamit.351",
      "Twitter link": "Not Available",
      "Place": "Not Available",
      "Designation": "Not Available",
      "Mobile No.": "Not Available"
    },
    {
      "ASSEMBLY SEAT NO": "174",
      "ASSEMBLY NAME": "Jalalpore",
      "CANDIDATE NAME": "Pradeepkumar Mishra",
      "Facebook Profile Link": "Not Available",
      "Twitter link": "Not Available",
      "Place": "Not Available",
      "Designation": "Not Available",
      "Mobile No.": "Not Available"
    },
    {
      "ASSEMBLY SEAT NO": "175",
      "ASSEMBLY NAME": "Navsari",
      "CANDIDATE NAME": "Upesh Patel",
      "Facebook Profile Link": "Not Available",
      "Twitter link": "Not Available",
      "Place": "Not Available",
      "Designation": "Not Available",
      "Mobile No.": "Not Available"
    },
    {
      "ASSEMBLY SEAT NO": "176",
      "ASSEMBLY NAME": "Gandevi (ST)",
      "CANDIDATE NAME": "PANKAJ L PATEL",
      "Facebook Profile Link": "https://www.facebook.com/pankajpatel.patel.733",
      "Twitter link": "Not Available",
      "Place": "Not Available",
      "Designation": "Not Available",
      "Mobile No.": "Not Available"
    },
    {
      "ASSEMBLY SEAT NO": "177",
      "ASSEMBLY NAME": "Vansda (ST)",
      "CANDIDATE NAME": "PANKAJ PATEL",
      "Facebook Profile Link": "Not Available",
      "Twitter link": "Not Available",
      "Place": "Not Available",
      "Designation": "Not Available",
      "Mobile No.": "Not Available"
    },
    {
      "ASSEMBLY SEAT NO": "178",
      "ASSEMBLY NAME": "Dharampur (ST)",
      "CANDIDATE NAME": "Kamelsh Patel",
      "Facebook Profile Link": "Not Available",
      "Twitter link": "Not Available",
      "Place": "Not Available",
      "Designation": "Not Available",
      "Mobile No.": "Not Available"
    },
    {
      "ASSEMBLY SEAT NO": "179",
      "ASSEMBLY NAME": "Valsad",
      "CANDIDATE NAME": "RAJU MARCHA",
      "Facebook Profile Link": "https://www.facebook.com/rajubhai.marcha",
      "Twitter link": "Not Available",
      "Place": "Not Available",
      "Designation": "Not Available",
      "Mobile No.": "Not Available"
    },
    {
      "ASSEMBLY SEAT NO": "180",
      "ASSEMBLY NAME": "Pardi",
      "CANDIDATE NAME": "Ketan Patel",
      "Facebook Profile Link": "Not Available",
      "Twitter link": "Not Available",
      "Place": "Not Available",
      "Designation": "Not Available",
      "Mobile No.": "Not Available"
    },
    {
      "ASSEMBLY SEAT NO": "181",
      "ASSEMBLY NAME": "Kaprada (ST)",
      "CANDIDATE NAME": "Jayendra gavit",
      "Facebook Profile Link": "Not Available",
      "Twitter link": "Not Available",
      "Place": "Not Available",
      "Designation": "Not Available",
      "Mobile No.": "Not Available"
    },
    {
      "ASSEMBLY SEAT NO": "182",
      "ASSEMBLY NAME": "Umbergaon(ST)",
      "CANDIDATE NAME": "Ashok Mohnabhai Patel",
      "Facebook Profile Link": "Not Available",
      "Twitter link": "Not Available",
      "Place": "Not Available",
      "Designation": "Not Available",
      "Mobile No.": "Not Available"
    },
    {
      "ASSEMBLY SEAT NO": "Youth Wing",
      "ASSEMBLY NAME": "Ahmedabad city and district",
      "CANDIDATE NAME": "kalpna bavskar ",
      "Facebook Profile Link": "Not Available",
      "Twitter link": "Not Available",
      "Place": "Prabhari",
      "Designation": "Not Available",
      "Mobile No.": "8758444824"
    },
    {
      "ASSEMBLY SEAT NO": "Youth Wing",
      "ASSEMBLY NAME": "sabarakantha, banaskantha, mahesana, patan ",
      "CANDIDATE NAME": "Vishvjeet desai",
      "Facebook Profile Link": "https://www.facebook.com/vishvajeetdesai",
      "Twitter link": "Gandhinagar",
      "Place": "Prabhari",
      "Designation": "Not Available",
      "Mobile No.": "9825375527"
    },
    {
      "ASSEMBLY SEAT NO": "Youth Wing",
      "ASSEMBLY NAME": "Mahisagar, Dahod, Panchmahal",
      "CANDIDATE NAME": "Bharat rathwa",
      "Facebook Profile Link": "Not Available",
      "Twitter link": "Not Available",
      "Place": "Prabhari",
      "Designation": "Not Available",
      "Mobile No.": "9925655397"
    },
    {
      "ASSEMBLY SEAT NO": "Youth Wing",
      "ASSEMBLY NAME": "Gandhinagar, Kheda, Aravali",
      "CANDIDATE NAME": "VirendraSingh Gohil",
      "Facebook Profile Link": "https://www.facebook.com/gohil.virendrasinh.5",
      "Twitter link": "Gandhinagar",
      "Place": "Prabhari",
      "Designation": "Not Available",
      "Mobile No.": "9574426561"
    },
    {
      "ASSEMBLY SEAT NO": "Youth Wing",
      "ASSEMBLY NAME": "Rajkot, Dwarka, Jamnagar, Morbi, Kutch",
      "CANDIDATE NAME": "YograjSingh Jadeja",
      "Facebook Profile Link": "Not Available",
      "Twitter link": "Not Available",
      "Place": "Prabhari",
      "Designation": "Not Available",
      "Mobile No.": "9898936264"
    },
    {
      "ASSEMBLY SEAT NO": "Youth Wing",
      "ASSEMBLY NAME": "Surat, Bharuch, Tapi, Dang, Navsari, Valsad",
      "CANDIDATE NAME": "Sukhdev gajera",
      "Facebook Profile Link": "https://www.facebook.com/sukhdev.gajera.3",
      "Twitter link": "Surat",
      "Place": "Prabhari",
      "Designation": "Not Available",
      "Mobile No.": "9825267737"
    },
    {
      "ASSEMBLY SEAT NO": "Youth Wing",
      "ASSEMBLY NAME": "Bhavnagar, Botad, Surendranagar",
      "CANDIDATE NAME": "Dharmaraj singh  kotila",
      "Facebook Profile Link": " ",
      "Twitter link": "Not Available",
      "Place": "Prabhari",
      "Designation": "Not Available",
      "Mobile No.": "9426147200"
    },
    {
      "ASSEMBLY SEAT NO": "Youth Wing",
      "ASSEMBLY NAME": "Chhota Udaipur, Narmada",
      "CANDIDATE NAME": "Vishal Dave",
      "Facebook Profile Link": "Not Available",
      "Twitter link": "Not Available",
      "Place": "Prabhari",
      "Designation": "Not Available",
      "Mobile No.": "9909891213"
    },
    {
      "ASSEMBLY SEAT NO": "Youth Wing",
      "ASSEMBLY NAME": "Vdodara, Anand",
      "CANDIDATE NAME": "Piyush Kakdiya",
      "Facebook Profile Link": "https://www.facebook.com/kakadiya.piyush.35",
      "Twitter link": "Vdodara",
      "Place": "Prabhari",
      "Designation": "Not Available",
      "Mobile No.": "9033319436"
    },
    {
      "ASSEMBLY SEAT NO": "Youth Wing",
      "ASSEMBLY NAME": "Junagadh, Gir Somanath, Amreli, Porbandar",
      "CANDIDATE NAME": "Ketul Kapdiya",
      "Facebook Profile Link": "https://www.facebook.com/ketul.kapadiya",
      "Twitter link": " Ahmedabad",
      "Place": "Prabhari",
      "Designation": "Not Available",
      "Mobile No.": "8160095492"
    }
  ]
